en_transformer/__init__.py
en_transformer/en_transformer.py
en_transformer/utils.py
En_transformer-1.6.6.dist-info/LICENSE
En_transformer-1.6.6.dist-info/METADATA
En_transformer-1.6.6.dist-info/WHEEL
En_transformer-1.6.6.dist-info/top_level.txt
En_transformer-1.6.6.dist-info/RECORD
