Metadata-Version: 2.1
Name: En-transformer
Version: 1.6.6
Summary: E(n)-Equivariant Transformer
Home-page: https://github.com/lucidrains/En-transformer
Author: Phil Wang
Author-email: lucidrains@gmail.com
License: MIT
Keywords: artificial intelligence,deep learning,equivariance,transformer
Classifier: Development Status :: 4 - Beta
Classifier: Intended Audience :: Developers
Classifier: Topic :: Scientific/Engineering :: Artificial Intelligence
Classifier: License :: OSI Approved :: MIT License
Classifier: Programming Language :: Python :: 3.6
License-File: LICENSE
Requires-Dist: einops >=0.8
Requires-Dist: einx
Requires-Dist: taylor-series-linear-attention >=0.1.4
Requires-Dist: torch >=1.7
